milvus_api/__init__.py
milvus_api/db_model/__init__.py
milvus_api/db_model/milvus_db.py
milvus_api/embed_model/__init__.py
milvus_api/embed_model/bgem3.py
milvus_api-0.2.1.2.dist-info/METADATA
milvus_api-0.2.1.2.dist-info/WHEEL
milvus_api-0.2.1.2.dist-info/top_level.txt
milvus_api-0.2.1.2.dist-info/RECORD
