Metadata-Version: 2.1
Name: milvus-api
Version: 0.2.1.2
Summary: A Milvus API used for quickly setting up a Milvus vector database
Author: ShengWen
Author-email: shengwen8785@example.com
Requires-Dist: pymilvus ==2.4.0
Requires-Dist: milvus-model ==0.2.0
Requires-Dist: pydantic ==2.7.0
Requires-Dist: tqdm ==4.66.2
Requires-Dist: FlagEmbedding ==1.2.9
Requires-Dist: torch ==2.2.2
Requires-Dist: numpy ==1.24.4
